pybpodgui_plugin/__init__.py
pybpodgui_plugin/__main__.py
pybpodgui_plugin/settings.py
pybpodgui_plugin/models/__init__.py
pybpodgui_plugin/models/board/__init__.py
pybpodgui_plugin/models/board/board_com.py
pybpodgui_plugin/models/board/board_dockwindow.py
pybpodgui_plugin/models/board/board_treenode.py
pybpodgui_plugin/models/board/board_uibusy.py
pybpodgui_plugin/models/board/board_window.py
pybpodgui_plugin/models/board/windows/__init__.py
pybpodgui_plugin/models/board/windows/code_editor.py
pybpodgui_plugin/models/board/windows/log_window.py
pybpodgui_plugin/models/experiment/__init__.py
pybpodgui_plugin/models/experiment/experiment_dockwindow.py
pybpodgui_plugin/models/experiment/experiment_treenode.py
pybpodgui_plugin/models/experiment/experiment_uibusy.py
pybpodgui_plugin/models/experiment/experiment_window.py
pybpodgui_plugin/models/project/__init__.py
pybpodgui_plugin/models/project/project_dockwindow.py
pybpodgui_plugin/models/project/project_treenode.py
pybpodgui_plugin/models/project/project_uibusy.py
pybpodgui_plugin/models/project/project_window.py
pybpodgui_plugin/models/projects/__init__.py
pybpodgui_plugin/models/projects/projects_treenode.py
pybpodgui_plugin/models/projects/projects_window.py
pybpodgui_plugin/models/session/__init__.py
pybpodgui_plugin/models/session/session_dockwindow.py
pybpodgui_plugin/models/session/session_signals.py
pybpodgui_plugin/models/session/session_treenode.py
pybpodgui_plugin/models/session/session_uibusy.py
pybpodgui_plugin/models/session/session_window.py
pybpodgui_plugin/models/setup/__init__.py
pybpodgui_plugin/models/setup/setup_com.py
pybpodgui_plugin/models/setup/setup_dockwindow.py
pybpodgui_plugin/models/setup/setup_treenode.py
pybpodgui_plugin/models/setup/setup_uibusy.py
pybpodgui_plugin/models/setup/setup_window.py
pybpodgui_plugin/models/setup/task_variable.py
pybpodgui_plugin/models/setup/board_task/__init__.py
pybpodgui_plugin/models/setup/board_task/board_task_uibusy.py
pybpod_gui_plugin-1.8.2.dist-info/LICENSE.md
pybpod_gui_plugin-1.8.2.dist-info/METADATA
pybpod_gui_plugin-1.8.2.dist-info/WHEEL
pybpod_gui_plugin-1.8.2.dist-info/top_level.txt
pybpod_gui_plugin-1.8.2.dist-info/RECORD
