Metadata-Version: 2.1
Name: pybpod-gui-plugin
Version: 1.8.2
Summary: pybpod-gui-plugin is a behavioral experiments control system written in Python 3 for Bpod
Home-page: https://github.com/pybpod/pybpod-gui-plugin
Author: ['Carlos Mão de Ferro', 'Ricardo Ribeiro', 'Luís Teixeira']
Author-email: cajomferro@gmail.com, ricardojvr@gmail.com, micboucinha@gmail.com
License: MIT
Platform: UNKNOWN
Requires-Dist: pyforms-gui
Requires-Dist: pyforms-generic-editor
Requires-Dist: pybpod-gui-api
Requires-Dist: pge-plugin-terminal
Requires-Dist: pybpod-gui-plugin-alyx
Requires-Dist: pybpod-gui-plugin-session-history
Requires-Dist: pybpod-gui-plugin-stmdiagram
Requires-Dist: pybpod-gui-plugin-timeline
Requires-Dist: pybpod-gui-plugin-trial-timeline
Requires-Dist: pybpod-gui-plugin-waveplayer
Requires-Dist: pybpod-gui-plugin-rotaryencoder
Requires-Dist: pybpod-gui-plugin-soundcard
